MANIFEST.in
quality_report.py
requirements.txt
setup.cfg
setup.py
hqlib/__init__.py
hqlib/commandlineargs.py
hqlib/filesystem.py
hqlib/log.py
hqlib/typing.py
hqlib/utils.py
hqlib/app/__init__.py
hqlib/app/dist/bundle.js
hqlib/app/html/index.html
hqlib/app/img/ashamed.png
hqlib/app/img/biggrin.png
hqlib/app/img/favicon.ico
hqlib/app/img/missing.png
hqlib/app/img/missing_source.png
hqlib/app/img/plain.png
hqlib/app/img/sad.png
hqlib/app/img/smile.png
hqlib/configuration/__init__.py
hqlib/configuration/configuration.py
hqlib/domain/__init__.py
hqlib/domain/base.py
hqlib/domain/measurement/__init__.py
hqlib/domain/measurement/directed_metric.py
hqlib/domain/measurement/measurable.py
hqlib/domain/measurement/metric.py
hqlib/domain/measurement/metric_source.py
hqlib/domain/measurement/metric_source_age_metric.py
hqlib/domain/measurement/metric_source_with_issues.py
hqlib/domain/measurement/percentage_metric.py
hqlib/domain/measurement/target.py
hqlib/domain/software_development/__init__.py
hqlib/domain/software_development/document.py
hqlib/domain/software_development/environment.py
hqlib/domain/software_development/process.py
hqlib/domain/software_development/product.py
hqlib/domain/software_development/project.py
hqlib/domain/software_development/requirement.py
hqlib/domain/software_development/team.py
hqlib/formatting/__init__.py
hqlib/formatting/base_formatter.py
hqlib/formatting/json_formatter.py
hqlib/metric/__init__.py
hqlib/metric/meta_metrics.py
hqlib/metric/metric_source_mixin.py
hqlib/metric/document/__init__.py
hqlib/metric/document/age.py
hqlib/metric/environment/__init__.py
hqlib/metric/environment/ci_jobs.py
hqlib/metric/environment/failing_ci_jobs.py
hqlib/metric/environment/unused_ci_jobs.py
hqlib/metric/environment/version_number.py
hqlib/metric/product/__init__.py
hqlib/metric/product/accessibility_metrics.py
hqlib/metric/product/aggregated_test_coverage_metrics.py
hqlib/metric/product/alerts_metrics.py
hqlib/metric/product/analysis_age.py
quality_report.egg-info/PKG-INFO
quality_report.egg-info/SOURCES.txt
quality_report.egg-info/dependency_links.txt
quality_report.egg-info/requires.txt
quality_report.egg-info/top_level.txt
