Metadata-Version: 1.1
Name: quality-report
Version: 2.93.3
Summary: Holistic Software Quality Reporting
Home-page: https://github.com/ICTU/quality-report
Author: ICTU
Author-email: frank.niessink@ictu.nl
License: Apache License, Version 2.0
Keywords: quality,software development,metrics,measurement
Platform: UNKNOWN
Classifier: Development Status :: 5 - Production/Stable
Classifier: Environment :: Web Environment
Classifier: Intended Audience :: Developers
Classifier: License :: OSI Approved :: Apache Software License
Classifier: Natural Language :: Dutch
Classifier: Operating System :: OS Independent
Classifier: Programming Language :: Python
Classifier: Programming Language :: Python :: 3 :: Only
Classifier: Programming Language :: JavaScript
Classifier: Topic :: Software Development :: Quality Assurance
